ktaga_lab/__init__.py
ktaga_lab/drivers/__init__.py
ktaga_lab/drivers/Keysight/Keysight_DSOX2014A.py
ktaga_lab/drivers/Keysight/Keysight_NanoVoltMeter.py
ktaga_lab/drivers/Keysight/Keysight_VNA.py
ktaga_lab/drivers/Keysight/__init__.py
ktaga_lab/drivers/SurugaSeiki/DS102.py
ktaga_lab/drivers/SurugaSeiki/__init__.py
ktaga_lab/drivers/TOEI/In_plane_prober.py
ktaga_lab/drivers/TOEI/__init__.py
ktaga_lab/drivers/Thorlabs/KCubeStepperMotor.py
ktaga_lab/drivers/Thorlabs/__init__.py
ktaga_lab/plot/__init__.py
ktaga_lab/plot/hvplot.py
ktaga_lab-0.1.12.dist-info/METADATA
ktaga_lab-0.1.12.dist-info/WHEEL
ktaga_lab-0.1.12.dist-info/RECORD
