Metadata-Version: 2.3
Name: ktaga-lab
Version: 0.1.12
Summary: Drivers and dependencies for the experimental setup and tools for data acquisition and analysis.
Requires-Python: >=3.12
Requires-Dist: dash>=2.18.0
Requires-Dist: holoviews[recommended]>=1.19.1
Requires-Dist: hvplot>=0.10.0
Requires-Dist: jupyter-ai>=2.24.0
Requires-Dist: jupyterlab>=4.2.5
Requires-Dist: kaleido==0.2.1
Requires-Dist: lmfit>=1.3.2
Requires-Dist: nbconvert>=7.16.4
Requires-Dist: nidaqmx>=1.0.1
Requires-Dist: pandoc>=2.4
Requires-Dist: pyserial>=3.5
Requires-Dist: pythonnet>=3.0.3
Requires-Dist: qcodes>=0.48.0
Requires-Dist: ruff>=0.6.4
Requires-Dist: scikit-rf>=1.3.0
Requires-Dist: sympy>=1.13.2
Provides-Extra: kt
Requires-Dist: jupyterlab-theme-solarized-dark>=3.0.1; extra == 'kt'
Requires-Dist: jupyterlab-vim>=4.1.3; extra == 'kt'
Provides-Extra: zurich
Requires-Dist: zhinst-qcodes>=0.5.4; extra == 'zurich'
Requires-Dist: zhinst>=24.7.3; extra == 'zurich'
